02_UART_FIFO_Subsystem/rtl/uart_tx.sv
// ============================================================
// Project 2: UART + FIFO RTL Subsystem
// Module: UART Transmitter
// Protocol: 8-N-1
// ============================================================

module uart_tx #(
    parameter int CLK_FREQ  = 50_000_000,
    parameter int BAUD_RATE = 115_200
)(
    input  logic       clk,
    input  logic       rst_n,

    // Transmit interface
    input  logic [7:0] tx_data,
    input  logic       tx_valid,
    output logic       tx_ready,

    // Serial output
    output logic       tx,

    // Status
    output logic       busy
);

    localparam int BAUD_DIV =
        (CLK_FREQ / BAUD_RATE);

    localparam int BAUD_CNT_WIDTH =
        (BAUD_DIV <= 1) ? 1 : $clog2(BAUD_DIV);

    logic [BAUD_CNT_WIDTH-1:0] baud_counter;

    logic [3:0] bit_index;

    logic [9:0] shift_reg;

    // --------------------------------------------------------
    // UART transmitter state
    //
    // Frame format:
    //
    //       START  DATA[7:0]              STOP
    //         0   D0 D1 D2 D3 D4 D5 D6 D7  1
    //
    // --------------------------------------------------------

    assign tx_ready = !busy;

    always_ff @(posedge clk or negedge rst_n) begin

        if (!rst_n) begin

            tx           <= 1'b1;
            busy         <= 1'b0;

            baud_counter <= '0;
            bit_index    <= '0;
            shift_reg    <= 10'b1111111111;

        end else begin

            // ------------------------------------------------
            // Idle state
            // ------------------------------------------------

            if (!busy) begin

                tx <= 1'b1;

                if (tx_valid) begin

                    // 8-N-1 frame
                    //
                    // bit 0 = start
                    // bits 1-8 = data
                    // bit 9 = stop

                    shift_reg <= {
                        1'b1,
                        tx_data,
                        1'b0
                    };

                    busy         <= 1'b1;
                    bit_index    <= 4'd0;
                    baud_counter <= '0;

                    tx <= 1'b0;
                end

            end

            // ------------------------------------------------
            // Active transmission
            // ------------------------------------------------

            else begin

                if (baud_counter == BAUD_DIV-1) begin

                    baud_counter <= '0;

                    if (bit_index == 4'd9) begin

                        // Transmission complete
                        busy      <= 1'b0;
                        bit_index <= '0;
                        tx        <= 1'b1;

                    end else begin

                        bit_index <= bit_index + 1'b1;

                        shift_reg <= {
                            1'b1,
                            shift_reg[9:1]
                        };

                        tx <= shift_reg[1];

                    end

                end else begin

                    baud_counter <= baud_counter + 1'b1;

                end

            end

        end

    end

endmodule

02_UART_FIFO_Subsystem/tb/uart_tx_tb.sv
`timescale 1ns/1ps

// ============================================================
// Project 2: UART + FIFO RTL Subsystem
// Testbench: UART Transmitter
// Protocol: 8-N-1
// ============================================================

module uart_tx_tb;

    // Use small values for fast simulation.
    localparam int CLK_FREQ  = 1_000_000;
    localparam int BAUD_RATE = 100_000;

    localparam int BAUD_DIV = CLK_FREQ / BAUD_RATE;

    logic clk;
    logic rst_n;

    logic [7:0] tx_data;
    logic       tx_valid;
    logic       tx_ready;

    logic       tx;
    logic       busy;

    integer pass_count;
    integer fail_count;

    // --------------------------------------------------------
    // DUT
    // --------------------------------------------------------

    uart_tx #(
        .CLK_FREQ  (CLK_FREQ),
        .BAUD_RATE (BAUD_RATE)
    ) dut (
        .clk       (clk),
        .rst_n     (rst_n),

        .tx_data   (tx_data),
        .tx_valid  (tx_valid),
        .tx_ready  (tx_ready),

        .tx        (tx),
        .busy      (busy)
    );

    // --------------------------------------------------------
    // Clock
    // --------------------------------------------------------

    initial begin
        clk = 1'b0;
        forever #5 clk = ~clk;
    end

    // --------------------------------------------------------
    // Waveform
    // --------------------------------------------------------

    initial begin
        $dumpfile("waveform/uart_tx_wave.vcd");
        $dumpvars(0, uart_tx_tb);
    end

    // --------------------------------------------------------
    // Check helper
    // --------------------------------------------------------

    task automatic check(
        input logic condition,
        input string message
    );
        begin
            if (condition) begin
                pass_count = pass_count + 1;
                $display("PASS: %s", message);
            end
            else begin
                fail_count = fail_count + 1;
                $display("FAIL: %s", message);
            end
        end
    endtask

    // --------------------------------------------------------
    // Transmit one byte
    // --------------------------------------------------------

    task automatic transmit_byte(
        input logic [7:0] data
    );
        begin

            // Wait until transmitter is ready
            wait (tx_ready == 1'b1);

            @(negedge clk);

            tx_data  = data;
            tx_valid = 1'b1;

            @(posedge clk);

            #1;

            tx_valid = 1'b0;

            check(
                busy == 1'b1,
                $sformatf(
                    "UART starts transmission of 0x%02h",
                    data
                )
            );

            // Wait until transmission completes
            wait (busy == 1'b0);

            check(
                tx == 1'b1,
                "TX returns to idle HIGH"
            );

        end
    endtask

    // --------------------------------------------------------
    // Main test
    // --------------------------------------------------------

    initial begin

        pass_count = 0;
        fail_count = 0;

        tx_data  = 8'h00;
        tx_valid = 1'b0;

        rst_n = 1'b0;

        $display("");
        $display("==============================================");
        $display("      UART TX VERIFICATION START");
        $display("==============================================");

        // ----------------------------------------------------
        // Reset
        // ----------------------------------------------------

        repeat (3)
            @(posedge clk);

        #1;

        check(
            tx == 1'b1,
            "TX idle state is HIGH after reset"
        );

        check(
            busy == 1'b0,
            "UART TX is not busy after reset"
        );

        check(
            tx_ready == 1'b1,
            "UART TX is ready after reset"
        );

        rst_n = 1'b1;

        // ----------------------------------------------------
        // Byte transmission tests
        // ----------------------------------------------------

        transmit_byte(8'hA5);

        transmit_byte(8'h3C);

        transmit_byte(8'h00);

        transmit_byte(8'hFF);

        // ----------------------------------------------------
        // Final result
        // ----------------------------------------------------

        $display("");
        $display("==============================================");
        $display("        UART TX VERIFICATION RESULT");
        $display("==============================================");

        $display("PASS COUNT = %0d", pass_count);
        $display("FAIL COUNT = %0d", fail_count);

        if (fail_count == 0) begin

            $display("");
            $display("==============================================");
            $display("          ALL UART TX TESTS PASSED");
            $display("==============================================");

        end
        else begin

            $display("");
            $display("==============================================");
            $display("          UART TX TESTS FAILED");
            $display("==============================================");

        end

        $finish;

    end

endmodule

02_UART_FIFO_Subsystem/waveform/uart_tx_wave.vcd
$date
	Thu Oct 01 18:47:59 2026
$end
$version
	Icarus Verilog
$end
$timescale
	1ps
$end
$scope module uart_tx_tb $end
$var wire 1 ! tx_ready $end
$var wire 1 " tx $end
$var wire 1 # busy $end
$var parameter 32 $ BAUD_DIV $end
$var parameter 32 % BAUD_RATE $end
$var parameter 32 & CLK_FREQ $end
$var reg 1 ' clk $end
$var reg 1 ( rst_n $end
$var reg 8 ) tx_data [7:0] $end
$var reg 1 * tx_valid $end
$var integer 32 + fail_count [31:0] $end
$var integer 32 , pass_count [31:0] $end
$scope module dut $end
$var wire 1 ' clk $end
$var wire 1 ( rst_n $end
$var wire 8 - tx_data [7:0] $end
$var wire 1 * tx_valid $end
$var wire 1 ! tx_ready $end
$var parameter 32 . BAUD_CNT_WIDTH $end
$var parameter 32 / BAUD_DIV $end
$var parameter 32 0 BAUD_RATE $end
$var parameter 32 1 CLK_FREQ $end
$var reg 4 2 baud_counter [3:0] $end
$var reg 4 3 bit_index [3:0] $end
$var reg 1 # busy $end
$var reg 10 4 shift_reg [9:0] $end
$var reg 1 " tx $end
$upscope $end
$scope task check $end
$upscope $end
$scope task transmit_byte $end
$upscope $end
$upscope $end
$enddefinitions $end
$comment Show the parameter values. $end
$dumpall
b11110100001001000000 1
b11000011010100000 0
b1010 /
b100 .
b11110100001001000000 &
b11000011010100000 %
b1010 $
$end
#0
$dumpvars
b1111111111 4
b0 3
b0 2
b0 -
b0 ,
b0 +
0*
b0 )
0(
0'
0#
1"
1!
$end
#5000
1'
#10000
0'
#15000
1'
#20000
0'
#25000
1'
#26000
1(
b11 ,
#30000
1*
b10100101 )
b10100101 -
0'
#35000
0"
0!
1#
b1101001010 4
1'
#36000
b100 ,
0*
#40000
0'
#45000
b1 2
1'
#50000
0'
#55000
b10 2
1'
#60000
0'
#65000
b11 2
1'
#70000
0'
#75000
b100 2
1'
#80000
0'
#85000
b101 2
1'
#90000
0'
#95000
b110 2
1'
#100000
0'
#105000
b111 2
1'
#110000
0'
#115000
b1000 2
1'
#120000
0'
#125000
b1001 2
1'
#130000
0'
#135000
1"
b1110100101 4
b1 3
b0 2
1'
#140000
0'
#145000
b1 2
1'
#150000
0'
#155000
b10 2
1'
#160000
0'
#165000
b11 2
1'
#170000
0'
#175000
b100 2
1'
#180000
0'
#185000
b101 2
1'
#190000
0'
#195000
b110 2
1'
#200000
0'
#205000
b111 2
1'
#210000
0'
#215000
b1000 2
1'
#220000
0'
#225000
b1001 2
1'
#230000
0'
#235000
0"
b1111010010 4
b10 3
b0 2
1'
#240000
0'
#245000
b1 2
1'
#250000
0'
#255000
b10 2
1'
#260000
0'
#265000
b11 2
1'
#270000
0'
#275000
b100 2
1'
#280000
0'
#285000
b101 2
1'
#290000
0'
#295000
b110 2
1'
#300000
0'
#305000
b111 2
1'
#310000
0'
#315000
b1000 2
1'
#320000
0'
#325000
b1001 2
1'
#330000
0'
#335000
1"
b1111101001 4
b11 3
b0 2
1'
#340000
0'
#345000
b1 2
1'
#350000
0'
#355000
b10 2
1'
#360000
0'
#365000
b11 2
1'
#370000
0'
#375000
b100 2
1'
#380000
0'
#385000
b101 2
1'
#390000
0'
#395000
b110 2
1'
#400000
0'
#405000
b111 2
1'
#410000
0'
#415000
b1000 2
1'
#420000
0'
#425000
b1001 2
1'
#430000
0'
#435000
0"
b1111110100 4
b100 3
b0 2
1'
#440000
0'
#445000
b1 2
1'
#450000
0'
#455000
b10 2
1'
#460000
0'
#465000
b11 2
1'
#470000
0'
#475000
b100 2
1'
#480000
0'
#485000
b101 2
1'
#490000
0'
#495000
b110 2
1'
#500000
0'
#505000
b111 2
1'
#510000
0'
#515000
b1000 2
1'
#520000
0'
#525000
b1001 2
1'
#530000
0'
#535000
b1111111010 4
b101 3
b0 2
1'
#540000
0'
#545000
b1 2
1'
#550000
0'
#555000
b10 2
1'
#560000
0'
#565000
b11 2
1'
#570000
0'
#575000
b100 2
1'
#580000
0'
#585000
b101 2
1'
#590000
0'
#595000
b110 2
1'
#600000
0'
#605000
b111 2
1'
#610000
0'
#615000
b1000 2
1'
#620000
0'
#625000
b1001 2
1'
#630000
0'
#635000
1"
b1111111101 4
b110 3
b0 2
1'
#640000
0'
#645000
b1 2
1'
#650000
0'
#655000
b10 2
1'
#660000
0'
#665000
b11 2
1'
#670000
0'
#675000
b100 2
1'
#680000
0'
#685000
b101 2
1'
#690000
0'
#695000
b110 2
1'
#700000
0'
#705000
b111 2
1'
#710000
0'
#715000
b1000 2
1'
#720000
0'
#725000
b1001 2
1'
#730000
0'
#735000
0"
b1111111110 4
b111 3
b0 2
1'
#740000
0'
#745000
b1 2
1'
#750000
0'
#755000
b10 2
1'
#760000
0'
#765000
b11 2
1'
#770000
0'
#775000
b100 2
1'
#780000
0'
#785000
b101 2
1'
#790000
0'
#795000
b110 2
1'
#800000
0'
#805000
b111 2
1'
#810000
0'
#815000
b1000 2
1'
#820000
0'
#825000
b1001 2
1'
#830000
0'
#835000
1"
b1111111111 4
b1000 3
b0 2
1'
#840000
0'
#845000
b1 2
1'
#850000
0'
#855000
b10 2
1'
#860000
0'
#865000
b11 2
1'
#870000
0'
#875000
b100 2
1'
#880000
0'
#885000
b101 2
1'
#890000
0'
#895000
b110 2
1'
#900000
0'
#905000
b111 2
1'
#910000
0'
#915000
b1000 2
1'
#920000
0'
#925000
b1001 2
1'
#930000
0'
#935000
b1001 3
b0 2
1'
#940000
0'
#945000
b1 2
1'
#950000
0'
#955000
b10 2
1'
#960000
0'
#965000
b11 2
1'
#970000
0'
#975000
b100 2
1'
#980000
0'
#985000
b101 2
1'
#990000
0'
#995000
b110 2
1'
#1000000
0'
#1005000
b111 2
1'
#1010000
0'
#1015000
b1000 2
1'
#1020000
0'
#1025000
b1001 2
1'
#1030000
0'
#1035000
b101 ,
b0 3
1!
0#
b0 2
1'
#1040000
1*
b111100 )
b111100 -
0'
#1045000
0"
0!
1#
b1001111000 4
1'
#1046000
b110 ,
0*
#1050000
0'
#1055000
b1 2
1'
#1060000
0'
#1065000
b10 2
1'
#1070000
0'
#1075000
b11 2
1'
#1080000
0'
#1085000
b100 2
1'
#1090000
0'
#1095000
b101 2
1'
#1100000
0'
#1105000
b110 2
1'
#1110000
0'
#1115000
b111 2
1'
#1120000
0'
#1125000
b1000 2
1'
#1130000
0'
#1135000
b1001 2
1'
#1140000
0'
#1145000
b1100111100 4
b1 3
b0 2
1'
#1150000
0'
#1155000
b1 2
1'
#1160000
0'
#1165000
b10 2
1'
#1170000
0'
#1175000
b11 2
1'
#1180000
0'
#1185000
b100 2
1'
#1190000
0'
#1195000
b101 2
1'
#1200000
0'
#1205000
b110 2
1'
#1210000
0'
#1215000
b111 2
1'
#1220000
0'
#1225000
b1000 2
1'
#1230000
0'
#1235000
b1001 2
1'
#1240000
0'
#1245000
b1110011110 4
b10 3
b0 2
1'
#1250000
0'
#1255000
b1 2
1'
#1260000
0'
#1265000
b10 2
1'
#1270000
0'
#1275000
b11 2
1'
#1280000
0'
#1285000
b100 2
1'
#1290000
0'
#1295000
b101 2
1'
#1300000
0'
#1305000
b110 2
1'
#1310000
0'
#1315000
b111 2
1'
#1320000
0'
#1325000
b1000 2
1'
#1330000
0'
#1335000
b1001 2
1'
#1340000
0'
#1345000
1"
b1111001111 4
b11 3
b0 2
1'
#1350000
0'
#1355000
b1 2
1'
#1360000
0'
#1365000
b10 2
1'
#1370000
0'
#1375000
b11 2
1'
#1380000
0'
#1385000
b100 2
1'
#1390000
0'
#1395000
b101 2
1'
#1400000
0'
#1405000
b110 2
1'
#1410000
0'
#1415000
b111 2
1'
#1420000
0'
#1425000
b1000 2
1'
#1430000
0'
#1435000
b1001 2
1'
#1440000
0'
#1445000
b1111100111 4
b100 3
b0 2
1'
#1450000
0'
#1455000
b1 2
1'
#1460000
0'
#1465000
b10 2
1'
#1470000
0'
#1475000
b11 2
1'
#1480000
0'
#1485000
b100 2
1'
#1490000
0'
#1495000
b101 2
1'
#1500000
0'
#1505000
b110 2
1'
#1510000
0'
#1515000
b111 2
1'
#1520000
0'
#1525000
b1000 2
1'
#1530000
0'
#1535000
b1001 2
1'
#1540000
0'
#1545000
b1111110011 4
b101 3
b0 2
1'
#1550000
0'
#1555000
b1 2
1'
#1560000
0'
#1565000
b10 2
1'
#1570000
0'
#1575000
b11 2
1'
#1580000
0'
#1585000
b100 2
1'
#1590000
0'
#1595000
b101 2
1'
#1600000
0'
#1605000
b110 2
1'
#1610000
0'
#1615000
b111 2
1'
#1620000
0'
#1625000
b1000 2
1'
#1630000
0'
#1635000
b1001 2
1'
#1640000
0'
#1645000
b1111111001 4
b110 3
b0 2
1'
#1650000
0'
#1655000
b1 2
1'
#1660000
0'
#1665000
b10 2
1'
#1670000
0'
#1675000
b11 2
1'
#1680000
0'
#1685000
b100 2
1'
#1690000
0'
#1695000
b101 2
1'
#1700000
0'
#1705000
b110 2
1'
#1710000
0'
#1715000
b111 2
1'
#1720000
0'
#1725000
b1000 2
1'
#1730000
0'
#1735000
b1001 2
1'
#1740000
0'
#1745000
0"
b1111111100 4
b111 3
b0 2
1'
#1750000
0'
#1755000
b1 2
1'
#1760000
0'
#1765000
b10 2
1'
#1770000
0'
#1775000
b11 2
1'
#1780000
0'
#1785000
b100 2
1'
#1790000
0'
#1795000
b101 2
1'
#1800000
0'
#1805000
b110 2
1'
#1810000
0'
#1815000
b111 2
1'
#1820000
0'
#1825000
b1000 2
1'
#1830000
0'
#1835000
b1001 2
1'
#1840000
0'
#1845000
b1111111110 4
b1000 3
b0 2
1'
#1850000
0'
#1855000
b1 2
1'
#1860000
0'
#1865000
b10 2
1'
#1870000
0'
#1875000
b11 2
1'
#1880000
0'
#1885000
b100 2
1'
#1890000
0'
#1895000
b101 2
1'
#1900000
0'
#1905000
b110 2
1'
#1910000
0'
#1915000
b111 2
1'
#1920000
0'
#1925000
b1000 2
1'
#1930000
0'
#1935000
b1001 2
1'
#1940000
0'
#1945000
1"
b1111111111 4
b1001 3
b0 2
1'
#1950000
0'
#1955000
b1 2
1'
#1960000
0'
#1965000
b10 2
1'
#1970000
0'
#1975000
b11 2
1'
#1980000
0'
#1985000
b100 2
1'
#1990000
0'
#1995000
b101 2
1'
#2000000
0'
#2005000
b110 2
1'
#2010000
0'
#2015000
b111 2
1'
#2020000
0'
#2025000
b1000 2
1'
#2030000
0'
#2035000
b1001 2
1'
#2040000
0'
#2045000
b111 ,
b0 3
1!
0#
b0 2
1'
#2050000
1*
b0 )
b0 -
0'
#2055000
0"
0!
1#
b1000000000 4
1'
#2056000
b1000 ,
0*
#2060000
0'
#2065000
b1 2
1'
#2070000
0'
#2075000
b10 2
1'
#2080000
0'
#2085000
b11 2
1'
#2090000
0'
#2095000
b100 2
1'
#2100000
0'
#2105000
b101 2
1'
#2110000
0'
#2115000
b110 2
1'
#2120000
0'
#2125000
b111 2
1'
#2130000
0'
#2135000
b1000 2
1'
#2140000
0'
#2145000
b1001 2
1'
#2150000
0'
#2155000
b1100000000 4
b1 3
b0 2
1'
#2160000
0'
#2165000
b1 2
1'
#2170000
0'
#2175000
b10 2
1'
#2180000
0'
#2185000
b11 2
1'
#2190000
0'
#2195000
b100 2
1'
#2200000
0'
#2205000
b101 2
1'
#2210000
0'
#2215000
b110 2
1'
#2220000
0'
#2225000
b111 2
1'
#2230000
0'
#2235000
b1000 2
1'
#2240000
0'
#2245000
b1001 2
1'
#2250000
0'
#2255000
b1110000000 4
b10 3
b0 2
1'
#2260000
0'
#2265000
b1 2
1'
#2270000
0'
#2275000
b10 2
1'
#2280000
0'
#2285000
b11 2
1'
#2290000
0'
#2295000
b100 2
1'
#2300000
0'
#2305000
b101 2
1'
#2310000
0'
#2315000
b110 2
1'
#2320000
0'
#2325000
b111 2
1'
#2330000
0'
#2335000
b1000 2
1'
#2340000
0'
#2345000
b1001 2
1'
#2350000
0'
#2355000
b1111000000 4
b11 3
b0 2
1'
#2360000
0'
#2365000
b1 2
1'
#2370000
0'
#2375000
b10 2
1'
#2380000
0'
#2385000
b11 2
1'
#2390000
0'
#2395000
b100 2
1'
#2400000
0'
#2405000
b101 2
1'
#2410000
0'
#2415000
b110 2
1'
#2420000
0'
#2425000
b111 2
1'
#2430000
0'
#2435000
b1000 2
1'
#2440000
0'
#2445000
b1001 2
1'
#2450000
0'
#2455000
b1111100000 4
b100 3
b0 2
1'
#2460000
0'
#2465000
b1 2
1'
#2470000
0'
#2475000
b10 2
1'
#2480000
0'
#2485000
b11 2
1'
#2490000
0'
#2495000
b100 2
1'
#2500000
0'
#2505000
b101 2
1'
#2510000
0'
#2515000
b110 2
1'
#2520000
0'
#2525000
b111 2
1'
#2530000
0'
#2535000
b1000 2
1'
#2540000
0'
#2545000
b1001 2
1'
#2550000
0'
#2555000
b1111110000 4
b101 3
b0 2
1'
#2560000
0'
#2565000
b1 2
1'
#2570000
0'
#2575000
b10 2
1'
#2580000
0'
#2585000
b11 2
1'
#2590000
0'
#2595000
b100 2
1'
#2600000
0'
#2605000
b101 2
1'
#2610000
0'
#2615000
b110 2
1'
#2620000
0'
#2625000
b111 2
1'
#2630000
0'
#2635000
b1000 2
1'
#2640000
0'
#2645000
b1001 2
1'
#2650000
0'
#2655000
b1111111000 4
b110 3
b0 2
1'
#2660000
0'
#2665000
b1 2
1'
#2670000
0'
#2675000
b10 2
1'
#2680000
0'
#2685000
b11 2
1'
#2690000
0'
#2695000
b100 2
1'
#2700000
0'
#2705000
b101 2
1'
#2710000
0'
#2715000
b110 2
1'
#2720000
0'
#2725000
b111 2
1'
#2730000
0'
#2735000
b1000 2
1'
#2740000
0'
#2745000
b1001 2
1'
#2750000
0'
#2755000
b1111111100 4
b111 3
b0 2
1'
#2760000
0'
#2765000
b1 2
1'
#2770000
0'
#2775000
b10 2
1'
#2780000
0'
#2785000
b11 2
1'
#2790000
0'
#2795000
b100 2
1'
#2800000
0'
#2805000
b101 2
1'
#2810000
0'
#2815000
b110 2
1'
#2820000
0'
#2825000
b111 2
1'
#2830000
0'
#2835000
b1000 2
1'
#2840000
0'
#2845000
b1001 2
1'
#2850000
0'
#2855000
b1111111110 4
b1000 3
b0 2
1'
#2860000
0'
#2865000
b1 2
1'
#2870000
0'
#2875000
b10 2
1'
#2880000
0'
#2885000
b11 2
1'
#2890000
0'
#2895000
b100 2
1'
#2900000
0'
#2905000
b101 2
1'
#2910000
0'
#2915000
b110 2
1'
#2920000
0'
#2925000
b111 2
1'
#2930000
0'
#2935000
b1000 2
1'
#2940000
0'
#2945000
b1001 2
1'
#2950000
0'
#2955000
1"
b1111111111 4
b1001 3
b0 2
1'
#2960000
0'
#2965000
b1 2
1'
#2970000
0'
#2975000
b10 2
1'
#2980000
0'
#2985000
b11 2
1'
#2990000
0'
#2995000
b100 2
1'
#3000000
0'
#3005000
b101 2
1'
#3010000
0'
#3015000
b110 2
1'
#3020000
0'
#3025000
b111 2
1'
#3030000
0'
#3035000
b1000 2
1'
#3040000
0'
#3045000
b1001 2
1'
#3050000
0'
#3055000
b1001 ,
b0 3
1!
0#
b0 2
1'
#3060000
1*
b11111111 )
b11111111 -
0'
#3065000
0"
0!
1#
b1111111110 4
1'
#3066000
b1010 ,
0*
#3070000
0'
#3075000
b1 2
1'
#3080000
0'
#3085000
b10 2
1'
#3090000
0'
#3095000
b11 2
1'
#3100000
0'
#3105000
b100 2
1'
#3110000
0'
#3115000
b101 2
1'
#3120000
0'
#3125000
b110 2
1'
#3130000
0'
#3135000
b111 2
1'
#3140000
0'
#3145000
b1000 2
1'
#3150000
0'
#3155000
b1001 2
1'
#3160000
0'
#3165000
1"
b1111111111 4
b1 3
b0 2
1'
#3170000
0'
#3175000
b1 2
1'
#3180000
0'
#3185000
b10 2
1'
#3190000
0'
#3195000
b11 2
1'
#3200000
0'
#3205000
b100 2
1'
#3210000
0'
#3215000
b101 2
1'
#3220000
0'
#3225000
b110 2
1'
#3230000
0'
#3235000
b111 2
1'
#3240000
0'
#3245000
b1000 2
1'
#3250000
0'
#3255000
b1001 2
1'
#3260000
0'
#3265000
b10 3
b0 2
1'
#3270000
0'
#3275000
b1 2
1'
#3280000
0'
#3285000
b10 2
1'
#3290000
0'
#3295000
b11 2
1'
#3300000
0'
#3305000
b100 2
1'
#3310000
0'
#3315000
b101 2
1'
#3320000
0'
#3325000
b110 2
1'
#3330000
0'
#3335000
b111 2
1'
#3340000
0'
#3345000
b1000 2
1'
#3350000
0'
#3355000
b1001 2
1'
#3360000
0'
#3365000
b11 3
b0 2
1'
#3370000
0'
#3375000
b1 2
1'
#3380000
0'
#3385000
b10 2
1'
#3390000
0'
#3395000
b11 2
1'
#3400000
0'
#3405000
b100 2
1'
#3410000
0'
#3415000
b101 2
1'
#3420000
0'
#3425000
b110 2
1'
#3430000
0'
#3435000
b111 2
1'
#3440000
0'
#3445000
b1000 2
1'
#3450000
0'
#3455000
b1001 2
1'
#3460000
0'
#3465000
b100 3
b0 2
1'
#3470000
0'
#3475000
b1 2
1'
#3480000
0'
#3485000
b10 2
1'
#3490000
0'
#3495000
b11 2
1'
#3500000
0'
#3505000
b100 2
1'
#3510000
0'
#3515000
b101 2
1'
#3520000
0'
#3525000
b110 2
1'
#3530000
0'
#3535000
b111 2
1'
#3540000
0'
#3545000
b1000 2
1'
#3550000
0'
#3555000
b1001 2
1'
#3560000
0'
#3565000
b101 3
b0 2
1'
#3570000
0'
#3575000
b1 2
1'
#3580000
0'
#3585000
b10 2
1'
#3590000
0'
#3595000
b11 2
1'
#3600000
0'
#3605000
b100 2
1'
#3610000
0'
#3615000
b101 2
1'
#3620000
0'
#3625000
b110 2
1'
#3630000
0'
#3635000
b111 2
1'
#3640000
0'
#3645000
b1000 2
1'
#3650000
0'
#3655000
b1001 2
1'
#3660000
0'
#3665000
b110 3
b0 2
1'
#3670000
0'
#3675000
b1 2
1'
#3680000
0'
#3685000
b10 2
1'
#3690000
0'
#3695000
b11 2
1'
#3700000
0'
#3705000
b100 2
1'
#3710000
0'
#3715000
b101 2
1'
#3720000
0'
#3725000
b110 2
1'
#3730000
0'
#3735000
b111 2
1'
#3740000
0'
#3745000
b1000 2
1'
#3750000
0'
#3755000
b1001 2
1'
#3760000
0'
#3765000
b111 3
b0 2
1'
#3770000
0'
#3775000
b1 2
1'
#3780000
0'
#3785000
b10 2
1'
#3790000
0'
#3795000
b11 2
1'
#3800000
0'
#3805000
b100 2
1'
#3810000
0'
#3815000
b101 2
1'
#3820000
0'
#3825000
b110 2
1'
#3830000
0'
#3835000
b111 2
1'
#3840000
0'
#3845000
b1000 2
1'
#3850000
0'
#3855000
b1001 2
1'
#3860000
0'
#3865000
b1000 3
b0 2
1'
#3870000
0'
#3875000
b1 2
1'
#3880000
0'
#3885000
b10 2
1'
#3890000
0'
#3895000
b11 2
1'
#3900000
0'
#3905000
b100 2
1'
#3910000
0'
#3915000
b101 2
1'
#3920000
0'
#3925000
b110 2
1'
#3930000
0'
#3935000
b111 2
1'
#3940000
0'
#3945000
b1000 2
1'
#3950000
0'
#3955000
b1001 2
1'
#3960000
0'
#3965000
b1001 3
b0 2
1'
#3970000
0'
#3975000
b1 2
1'
#3980000
0'
#3985000
b10 2
1'
#3990000
0'
#3995000
b11 2
1'
#4000000
0'
#4005000
b100 2
1'
#4010000
0'
#4015000
b101 2
1'
#4020000
0'
#4025000
b110 2
1'
#4030000
0'
#4035000
b111 2
1'
#4040000
0'
#4045000
b1000 2
1'
#4050000
0'
#4055000
b1001 2
1'
#4060000
0'
#4065000
b1011 ,
b0 3
1!
0#
b0 2
1'
